pyjacan/__init__.py
pyjacan/core.py
pyjacan-1.1.0.dist-info/licenses/LICENSE.txt
pyjacan-1.1.0.dist-info/METADATA
pyjacan-1.1.0.dist-info/WHEEL
pyjacan-1.1.0.dist-info/top_level.txt
pyjacan-1.1.0.dist-info/RECORD
