Metadata-Version: 2.4
Name: pyjacan
Version: 1.1.0
Summary: Analytical Jacobian builder for stencil-based systems (differnetial equation + boundary conditions)
Author-email: Marcel Čarman <s242989@student.dtu.dk>, Nejc Jeraj <nj2021@student.uni-lj.si>, Tomaž Katrašnik <tomaz.katrasnik@fs.uni-lj.si>, Klemen Zelič <klemen.zelic@fs.uni-lj.si>
License: CC BY-NC-SA 4.0
Project-URL: Homepage, https://github.com/mc8970/Function-to-Jacobian
Requires-Python: >=3.9
License-File: LICENSE.txt
Requires-Dist: numpy>=1.24
Requires-Dist: sympy>=1.12
Requires-Dist: scipy>=1.11
Requires-Dist: matplotlib>=3.8
Dynamic: license-file
